mimeparser/__init__.py
mimeparser/mimeparser.py
xml2dict/__init__.py
xml2dict/xml2dict.py
parsing_tools-2.0.0.dist-info/METADATA
parsing_tools-2.0.0.dist-info/WHEEL
parsing_tools-2.0.0.dist-info/licenses/LICENSE.txt
parsing_tools-2.0.0.dist-info/RECORD
