Metadata-Version: 2.4
Name: parsing_tools
Version: 2.0.0
Summary: Python Parsing Tools
Project-URL: url, https://github.com/cnobile2012/parsing_tools
Project-URL: Repository, https://github.com/cnobile2012/parsing_tools
Author-email: "Carl J. Nobile" <carl.nobile@gmail.com>
Maintainer-email: "Carl J. Nobile" <carl.nobile@gmail.com>
License-Expression: MIT
License-File: LICENSE.txt
Keywords: mime,xml
Classifier: Development Status :: 5 - Production/Stable
Classifier: Intended Audience :: Developers
Classifier: Operating System :: OS Independent
Classifier: Programming Language :: Python
Classifier: Programming Language :: Python :: 3.8
Classifier: Programming Language :: Python :: 3.9
Classifier: Programming Language :: Python :: 3.10
Classifier: Programming Language :: Python :: 3.11
Classifier: Programming Language :: Python :: 3.12
Classifier: Programming Language :: Python :: 3.13
Requires-Python: >=3.8
Requires-Dist: defusedxml
Requires-Dist: six
